{"context_23" : "NA", "context_24" : "NA", "subject_terms_4" : "NA", "subject_terms_3" : "Peranakan costumes", "context_2" : "NA", "materials_name" : "muslin", "creator_2" : "NA", "object_work_type" : "panels (costume components) sections (general, part)", "inscriptions" : "", "object_colour" : "multicolored", "context_18" : "NA", "physical_appearance" : "This is a panel of fabric. It holds a sketched design of a scalloped border with floral details. A segment of the fabric is embroidered with ivory thread.", "context_22" : "NA", "context_14" : "NA", "context_11" : "NA", "sgcool_label_text" : "This panel of muslin fabric shows a sketched design of scalloped border with floral details, a segment of which has been embroidered with ivory coloured thread. This embroidered panel may have been intended for a kebaya with tapered ends. These kebayas were popular in the 1930s and many were commissioned by Peranakan women. It is part of a donation which contains a mixture of garments worn by Peranakan men and women.", "preference" : "main", "context_6" : "NA", "creator_1" : "NA", "context_1" : "NA", "edition_description" : "NA", "title_language" : "", "context_19" : "NA", "context_21" : "NA", "context_15" : "NA", "context_5" : "NA", "title_text" : "Fabric Panel with Kebaya Design and Embroidery", "inscription_language" : "", "creation_date" : "early-mid 20th century", "subject_terms_1" : "flowers (motifs) Peranakan unfinished kebayas embroidery (visual works)", "context_16" : "NA", "context_10" : "NA", "context_4" : "NA", "context_8" : "NA", "creator_role" : "NA", "context_20" : "NA", "styles_periods_indexing_terms" : "NA", "accession_no_csv" : "2016-00700", "shape" : "irregular", "creation_place_original_location" : "Java (Indonesia)", "subject_terms_2" : "Motifs Peranakan (Asian people) Textiles Embroidery", "Image" : "", "context_3" : "NA", "context_9" : "NA", "techniques_name" : "sewing (needleworking technique) embroidering", "scale_type" : "NA", "context_13" : "NA", "context_7" : "NA", "context_12" : "NA", "context_17" : "NA"}