{"context_23" : "NA", "context_24" : "NA", "subject_terms_4" : "NA", "subject_terms_3" : "Letters Kandiar, Appavoo", "context_2" : "NA", "materials_name" : "paper (fiber product)", "creator_2" : "Not indicated", "object_work_type" : "letters (correspondence)", "inscriptions" : "", "object_colour" : "multicoloured", "context_18" : "NA", "physical_appearance" : "The image shows a letter which is light red in colour. All the words in the letters are handwritten, either in blue or black ink. At the top of the letter, there is a simple line diagram that starts from one heading and then branches out into four sub-headings. The body of the letter contains fourteen lines and the conclusion in the next paragraph contains two horizontal lines of English words. After the concluding statements, the letter is signed off. The letter has several brown spots, most of which are near to its vertical mid-point", "context_22" : "NA", "context_14" : "NA", "context_11" : "NA", "sgcool_label_text" : "A native of Karuvakurichi village, near Mannargudi town in Tamil Nadu, S. Appavoo Kandiar was a general contractor specializing in pipe and cable laying, handling of cargo and a concrete bricks supplier. Mr.Kandiar was a successful contractor; called a millionaire by the Straits Times in 1957, he owned properties in Bukit Timah and Coronation Road areas. He was a contemporary of Indian pioneers such as P.Govindasamy Pillai, Govindasamy Sarangapany, Pakkirisami Pillai, and had friendly associations with them.", "preference" : "main alternate", "context_6" : "NA", "creator_1" : "Not indicated", "context_1" : "NA", "edition_description" : "NA", "title_language" : "", "context_19" : "NA", "context_21" : "NA", "context_15" : "NA", "context_5" : "NA", "title_text" : "Life events of Mr.Appavoo Kandiar Letter stating  life events of Mr.Appavoo Kandiar", "inscription_language" : "", "creation_date" : "1953", "subject_terms_1" : "handwriting biographies (documents) diagrams", "context_16" : "NA", "context_10" : "NA", "context_4" : "NA", "context_8" : "NA", "creator_role" : "Not indicated", "context_20" : "NA", "styles_periods_indexing_terms" : "NA", "accession_no_csv" : "2016-00100", "shape" : "rectangular", "creation_place_original_location" : "Singapore", "subject_terms_2" : "Letters Writing Biography Charts, diagrams, etc.", "Image" : "", "context_3" : "NA", "context_9" : "NA", "techniques_name" : "writing (process)", "scale_type" : "NA", "context_13" : "NA", "context_7" : "NA", "context_12" : "NA", "context_17" : "NA"}