{"context_23" : "NA", "context_24" : "NA", "subject_terms_4" : "NA", "subject_terms_3" : "Chinese costumes", "context_2" : "NA", "materials_name" : "silk (textile) gold thread", "creator_2" : "NA", "object_work_type" : "skirts (garments) womenswear", "inscriptions" : "", "object_colour" : "multicolored", "context_18" : "NA", "physical_appearance" : "This is a skirt with pleated sides. The skirt has a brown waistband. It is made of pink patterned cloth. In the middle, there is a panel bordered by blue floral embroidery. In the center, there are two medallions bordered by a gold thread. In the medallions, there is a depiction of a woman with a child in her arms, and a man in official robes in a garden.", "context_22" : "NA", "context_14" : "NA", "context_11" : "NA", "sgcool_label_text" : "The skirt was worn with a loosely-fitted jacket. Taken together, the two-piece ensemble was known as aoqun, a popular form of Han Chinese dress during the Qing dynasty. The sides of the skirt are finely pleated.  Set against a gold thread background, two medallions depict a woman holding a child in her arms and a man in official robes strolling in a garden. Skirts with pleated sides became very popular during the Qing dynasty. The fact that some skirts had as many as 100 pleats earned this type of garment the name ‘fish-scale skirt of 100 pleats’.", "preference" : "alternate main", "context_6" : "NA", "creator_1" : "NA", "context_1" : "NA", "edition_description" : "NA", "title_language" : "", "context_19" : "NA", "context_21" : "NA", "context_15" : "NA", "context_5" : "NA", "title_text" : "Pink Chinese skirt Pink Han Chinese skirt", "inscription_language" : "", "creation_date" : "late Qing dynasty", "subject_terms_1" : "foliage (motif) flower (motif) embroidery (visual works) folk costume", "context_16" : "NA", "context_10" : "NA", "context_4" : "NA", "context_8" : "NA", "creator_role" : "NA", "context_20" : "NA", "styles_periods_indexing_terms" : "Han (Chinese, culture, style, period)", "accession_no_csv" : "2016-00311", "shape" : "irregular", "creation_place_original_location" : "China", "subject_terms_2" : "Skirts Ethnic costume Embroidery Motifs", "Image" : "", "context_3" : "NA", "context_9" : "NA", "techniques_name" : "sewing (needleworking technique) embroidering", "scale_type" : "NA", "context_13" : "NA", "context_7" : "NA", "context_12" : "NA", "context_17" : "NA"}