{"context_23" : "NA", "context_24" : "NA", "subject_terms_4" : "NA", "subject_terms_3" : "Geographical areas and countries", "context_2" : "NA", "materials_name" : "paper (fiber product)", "creator_2" : "NA", "object_work_type" : "maps (documents)", "inscriptions" : "", "object_colour" : "multicoloured", "context_18" : "NA", "physical_appearance" : "This is a World War II map of Southeast Asia and Northern Australia. It is an overview of the Southern Co-Prosperity Sphere. It was issued by the Japanese Intelligency agency.", "context_22" : "NA", "context_14" : "NA", "context_11" : "NA", "sgcool_label_text" : "This map provides an overview of the Southern Co-Prosperity Sphere, of northern Australia and Southeast Asia. Issued by the Japanese intelligence agency, there is also an inset map in the lower left corner that depicts Australia and Southeast Asia in the larger region.", "preference" : "main", "context_6" : "NA", "creator_1" : "NA", "context_1" : "NA", "edition_description" : "NA", "title_language" : "", "context_19" : "NA", "context_21" : "NA", "context_15" : "NA", "context_5" : "NA", "title_text" : "WWII Japanese Map of Southeast Asia and Northern Australia", "inscription_language" : "", "creation_date" : "1942", "subject_terms_1" : "cartography (discipline)", "context_16" : "NA", "context_10" : "NA", "context_4" : "NA", "context_8" : "NA", "creator_role" : "NA", "context_20" : "NA", "styles_periods_indexing_terms" : "NA", "accession_no_csv" : "2017-00846", "shape" : "Rectangular", "creation_place_original_location" : "Japan", "subject_terms_2" : "Maps  Greater East Asia Co-prosperity Sphere  Southeast Asia  Australia, Northern  World War, 1939-1945 Cartography", "Image" : "", "context_3" : "NA", "context_9" : "NA", "techniques_name" : "mapmaking (process)", "scale_type" : "0:500km", "context_13" : "NA", "context_7" : "NA", "context_12" : "NA", "context_17" : "NA"}