{"context_23" : "NA", "context_24" : "NA", "subject_terms_4" : "", "subject_terms_3" : "Lu, Earl Ming-Teh", "context_2" : "NA", "materials_name" : "wood (plant material)", "creator_2" : "NA", "object_work_type" : "combs (hair ornaments)", "inscriptions" : "", "object_colour" : "multicolored", "context_18" : "NA", "physical_appearance" : "This is a ceremonial comb. The comb has fine teeth on either side. The two sides are joint in the center by a dark brown block. Along the block, there is an inscription in gold. The ends of the teeth are rounded by a white plastic.", "context_22" : "NA", "context_14" : "NA", "context_11" : "NA", "sgcool_label_text" : "This comb belonged to a majie, a Cantonese female domestic helper. In adherence to tradition, majies underwent a sor hei (combing up) ceremony where they took an oath before a statuette of Guan Yin (Goddess of Mercy) to remain unmarried and celibate. Sor hei, in literal terms, means to “comb up” the hair into a bun or plait. Many majies chose to undergo sor hei as a socially accepted form of singlehood, choosing sworn sisterhood as an alternative to the institution of marriage.", "preference" : "main", "context_6" : "NA", "creator_1" : "NA", "context_1" : "NA", "edition_description" : "NA", "title_language" : "", "context_19" : "NA", "context_21" : "NA", "context_15" : "NA", "context_5" : "NA", "title_text" : "Majie’s Comb", "inscription_language" : "", "creation_date" : "Mid-20th century", "subject_terms_1" : "maids (servants) ceremonial objects customs (social concepts) cultural ceremonies", "context_16" : "NA", "context_10" : "NA", "context_4" : "NA", "context_8" : "NA", "creator_role" : "NA", "context_20" : "NA", "styles_periods_indexing_terms" : "NA", "accession_no_csv" : "2017-00898", "shape" : "irregular", "creation_place_original_location" : "Singapore", "subject_terms_2" : "Household employees Combs Ceremonial objects Rites and ceremonies", "Image" : "", "context_3" : "NA", "context_9" : "NA", "techniques_name" : "woodcarving", "scale_type" : "NA", "context_13" : "NA", "context_7" : "NA", "context_12" : "NA", "context_17" : "NA"}