{"context_23" : "NA", "context_24" : "NA", "subject_terms_4" : "NA", "subject_terms_3" : "visual arts  Mixed media artists", "context_2" : "NA", "materials_name" : "cloth  bamboo (material)", "creator_2" : "Norberto Roldan", "object_work_type" : "collages (visual works)  fabric art (visual works)", "inscriptions" : "", "object_colour" : "multicoloured", "context_18" : "NA", "physical_appearance" : "\"This is an assemblage consisting of small herb bottles, baby amulet beads, silk screen images of families, as well as embroidery. The base fabric utilized is that of traditional Visayan \"\"patadyong\"\". The central image is framed in a square\/diamond-shaped embroidery while the other two silkscreen images are on the top right and left corners.  Triangular stitching with baby amulet beads frames each corner of the fabric. \"", "context_22" : "NA", "context_14" : "NA", "context_11" : "NA", "sgcool_label_text" : "NA", "preference" : "main", "context_6" : "NA", "creator_1" : "Roldan, Norberto", "context_1" : "NA", "edition_description" : "NA", "title_language" : "", "context_19" : "NA", "context_21" : "NA", "context_15" : "NA", "context_5" : "NA", "title_text" : "The Wedding in Negros", "inscription_language" : "", "creation_date" : "1989", "subject_terms_1" : "material culture (genre)  memory  group identity  collective biographies biography (genre)  ethnicity", "context_16" : "NA", "context_10" : "NA", "context_4" : "NA", "context_8" : "NA", "creator_role" : "artists (visual artists)", "context_20" : "NA", "styles_periods_indexing_terms" : "NA", "accession_no_csv" : "2017-00229", "shape" : "Rectangular", "creation_place_original_location" : "Philippines", "subject_terms_2" : "Material culture Visayan Islands (Philippines) Group identity Ethnicity Collective memory  Biography", "Image" : "", "context_3" : "NA", "context_9" : "NA", "techniques_name" : "stitching (generic process)  embroidering  screen printing  weaving  beading (process)", "scale_type" : "NA", "context_13" : "NA", "context_7" : "NA", "context_12" : "NA", "context_17" : "NA"}