{
  "subject_terms_4": "are displayed on both of the invitation cards. The image of an man in a trishaw is displayed on both the invitation cards as well.\"",
  "subject_terms_3": "\"\"15 - 18 November 2012\"\"",
  "context_2": "Invitation cards",
  "materials_name": "paper (fiber product)",
  "creator_2": "Not indicated",
  "object_work_type": "invitations",
  "object_colour": "multicoloured",
  "physical_appearance": "\"The image features 2 rectangular sets of invitation cards \"\"Affordable Art Fair\"\" is printed on the left hand side of both invitation cards. The phrase",
  "context_11": "Will Ramsay",
  "preference": "main alternate",
  "context_6": "fairs",
  "creator_1": "Not indicated",
  "context_1": "cards (information artifacts)",
  "context_5": "Affordable Art Fair",
  "title_text": "Affordable Art Fair (2) Invite cards for Affordable Art Fair (2)",
  "creation_date": "5-Mar",
  "subject_terms_1": "\"\"I am an Art Collector\"\" fairs collectors Contemporary (style of art)",
  "context_10": "F1 Pit Building",
  "context_8": "20171115",
  "accession_no_csv": "2014-00906",
  "shape": "rectangular",
  "creation_place_original_location": "Singapore",
  "subject_terms_2": "and the dates Art fairs Art Collectors and collecting Art, Modern 21st century",
  "context_3": "Arts events",
  "context_9": "20171117",
  "techniques_name": "printing (process)",
  "context_7": "15th - 17th Nov 2012",
  "context_12": "creators"
}