{"subject_terms_3" : "Ethnic costume Chinese costume", "materials_name" : "cotton (textile) piping (trimming)", "object_work_type" : "folk costume", "object_colour" : "multicoloured", "physical_appearance" : "This is a grey samfoo with long sleeves and long pants. A collar is present as well. This samfoo contains green piping at its collar, side fastenings, and at the edges of the cuffs. There are no visible tears on the samfoo. Green and yellow floral motifs appear all over the outfit. There are vertical crease lines present on both the shirt and pants.", "sgcool_label_text" : "This is a cotton samfoo with green and yellow floral motifs and green piping. The samfoo is a traditional Chinese outfit which consists of a top (‘sam’) with side fastenings and a mandarin collar, worn over a pair of pants (‘foo’). Traditionally, the samfoo is loose fitting and its cut makes it convenient for the wearer to carry out everyday activities.", "preference" : "main", "title_text" : "Samfoo with green and yellow floral motif", "creation_date" : "1960 - 1969", "subject_terms_1" : "floral patterns unisex clothing", "styles_periods_indexing_terms" : "Chinese (culture or style)", "accession_no_csv" : "2016-00174", "shape" : "irregular", "creation_place_original_location" : "Singapore", "subject_terms_2" : "Ethnic costume Motifs", "techniques_name" : "machine sewing (technique) piping (process)"}