{
  "subject_terms_3": "Indian music Performing Arts Musicians",
  "materials_name": "printing paper",
  "creator_2": "Unknown",
  "object_work_type": "invitations",
  "object_colour": "multicoloured",
  "physical_appearance": "\"The image shows an invitation card. It is rectangular in shape. It has an orange background. The invitation card is filled with the Tamil script. The date \"\"10-12-51\"\" is stated at the top right hand side. The initials \"\"M.V.\"\" are stated at the bottom right hand side. \"",
  "sgcool_label_text": "M.V.Gurusamy (b. 1920 in Seremban) was an accomplished percussionist and mridangam artiste as well as a renowned percussion teacher in Singapore. He arrived in Singapore and participated in the Indian classical music scene here. He was a member of the cultural contingent led by the then Minister for Culture, S. Rajaratnam, which visited and performed at various centres in Sarawak, Brunei and Sabah in 1965. He was the recipient of several titles including the Kala Ratna award given by the Singapore Indian Fine Arts Society in 1986.",
  "preference": "main",
  "title_text": "Invitation to concert (“Sangeetha Katcheri”)",
  "creation_date": "10-Dec-51",
  "subject_terms_1": "concerts (performances) musicians",
  "styles_periods_indexing_terms": "Not indicated",
  "accession_no_csv": "2016-00065",
  "shape": "rectangular",
  "creation_place_original_location": "Singapore",
  "subject_terms_2": "Invitation cards Concerts Musicians",
  "techniques_name": "printing (process)",
  "scale_type": "Not indicated"
}