{
  "subject_terms_3": "Indian food",
  "materials_name": "brass (alloy) bamboo (material)",
  "object_work_type": "steamers (cookware)",
  "object_colour": "multicoloured",
  "physical_appearance": "The image displays a puttu maker. It comprises of a pot as its base, with five tubes at the top. These five tubes can be detached from its base. All of the five tubes are wrapped with cloth and have ropes tied around them.",
  "sgcool_label_text": "This puttu maker is of highly unusual design, comprising of a brass pot, with five bamboo inserts. Puttu is a popular breakfast\/snack in Kerala, made of a mix of steamed broken rice and grated coconut. The mix of rice and coconut would be stuffed into the bamboo tubes, and then steamed by heating the water in the pot.",
  "preference": "main main",
  "title_text": "Puttu maker Puttu kudam",
  "creation_date": "1900 - 1999",
  "subject_terms_1": "kitchenware cooking utensils implements (object genre)",
  "accession_no_csv": "2016-00231",
  "shape": "irregular",
  "creation_place_original_location": "Kerala (India)",
  "subject_terms_2": "Food steamers Steaming (Cooking) Kitchen utensils",
  "techniques_name": "metalworking forming (physical activity)"
}