{
  "subject_terms_3": "Geographical areas and countries Trade and industry",
  "materials_name": "paper (fiber product)",
  "creator_2": "Henricus Hondius",
  "object_work_type": "maps  nautical charts",
  "object_colour": "multicoloured",
  "physical_appearance": "This is a map of Southeast Asia in the mid 17th century and its title can be found at the top. It is a colourful illustration, charts the numerous oceans of the region, has three cartouches, one coat of arms, and several sailing vessels",
  "sgcool_label_text": "Henricus Hondius's 1636 map of Southeast Asia was based on Willem Blaeu's map from the previous year. Both maps were vast improvements from earlier maps of the region, and present the extent of the trading influence of the Dutch East India Company. This map features a dedication in Latin to the wealthy Dutch merchant Christophoro Thisio.",
  "preference": "main",
  "creator_1": "Hondius, Hendrik, 1597-1651 Blaeu, Willem Janszoon, 1571-1638",
  "title_text": "Henricus Hondius’s map of Southeast Asia",
  "creation_date": "C. 1636",
  "subject_terms_1": "coats of arms  trade (function)  cartouches (ornament)",
  "creator_role": "engravers (printmakers) cartographers",
  "accession_no_csv": "2017-00055",
  "shape": "Rectangular",
  "creation_place_original_location": "Amsterdam (Netherlands)",
  "subject_terms_2": "Southeast Asia  Nederlandsche Oost-Indische Compagnie  Nautical charts  Business Hondius, Hendrik, 1597-1651",
  "techniques_name": "copper engraving (printing process)  hand coloring",
  "scale_type": "Not indicated"
}