{
  "id": "2017-00660",
  "title": "Bag Beaded bag",
  "source": "Bumblebee",
  "path": "./Data/json/",
  "content": "\n  accession_no_csv: 2017-00660\n\n  Image: \n\n  object_work_type: bags (costume accessories)\n\n  title_text: Bag Beaded bag\n\n  preference: alternate main\n\n  title_language: \n\n  creation_date: 20th century\n\n  creation_place_original_location: Gujarat (India)\n\n  inscriptions: \n\n  inscription_language: \n\n  shape: irregular\n\n  materials_name: glass (material) textile materials\n\n  techniques_name: sewing (needleworking technique) embroidering\n\n  object_colour: multicolored\n\n  physical_appearance: This is a bag featuring decorative beadwork embroidery. It is made from multicoloured textile with an opening at the top. The center features a stylized beaded design of two birds perched on either side of a deity figure. The left side of the bag is slightly torn.\n\n  subject_terms_1: beadwork (visual works) embroidery (visual works) birds (motifs) deities depictions (visual works)\n\n  subject_terms_2: Bags Embroidery Motifs Gods\n\n  subject_terms_3: Decorative arts\n\n  subject_terms_4: \n",
  "createdDate": "20201120223708",
  "version": 0,
  "latest": false,
  "roles": [],
  "metadata": {
    "accession_no_csv": "2017-00660",
    "Image": "",
    "object_work_type": "bags (costume accessories)",
    "title_text": "Bag Beaded bag",
    "preference": "alternate main",
    "title_language": "",
    "creation_date": "20th century",
    "creation_place_original_location": "Gujarat (India)",
    "inscriptions": "",
    "inscription_language": "",
    "shape": "irregular",
    "materials_name": "glass (material) textile materials",
    "techniques_name": "sewing (needleworking technique) embroidering",
    "object_colour": "multicolored",
    "physical_appearance": "This is a bag featuring decorative beadwork embroidery. It is made from multicoloured textile with an opening at the top. The center features a stylized beaded design of two birds perched on either side of a deity figure. The left side of the bag is slightly torn.",
    "subject_terms_1": "beadwork (visual works) embroidery (visual works) birds (motifs) deities depictions (visual works)",
    "subject_terms_2": "Bags Embroidery Motifs Gods",
    "subject_terms_3": "Decorative arts",
    "subject_terms_4": ""
  },
  "nlpDate": "20201120223708",
  "connectorId": 0,
  "tags": {}
}