{"subject_terms_4" : "visual arts", "subject_terms_3" : "Blue and white ware China Decorative arts Ceramics", "context_2" : "It was exhibited at the Exhibition of Chinese Blue-and-White Ceramics held at the National Museum of Singapore in 1978.", "materials_name" : "blue-and-white (ceramic glaze) porcelain (material)  cobalt blue (pigment)  clay  ceramic glaze", "object_work_type" : "porcelain (visual works)  dishes (object genre)  Ceramics (object genre)", "object_colour" : "multicoloured", "physical_appearance" : "\"This is a Qing dynasty dish and its interior is decorated with the \"\"China aster\"\" pattern. While the outer rim consists of repeated asters divided by a thin free-handed stroke", "preference" : "main", "context_6" : "18-Apr-78", "context_5" : "18-Apr-78", "title_text" : "Blue and white dish with aster pattern", "creation_date" : "Qing dynasty, late 17th or early 18th century", "subject_terms_1" : "the center of the dish is comprised of five aster flower heads surrounded by repeated swirl motifs. A leaf motif as well as three stickers and its accession number can be found on the underside of the dish. \" symbolism  floral patterns  stamps (marks)", "context_4" : "Apr-78", "context_8" : "National Museum (Singapore) curators", "styles_periods_indexing_terms" : "Qing (dynastic styles and periods)  Chinese ceramics styles", "accession_no_csv" : "2017-00262", "shape" : "concave", "creation_place_original_location" : "China", "subject_terms_2" : "repeated motif China aster Porcelain, Chinese Ming- Qing dynasties, 1368-1912 China painting", "context_3" : "exhibitions (events)", "context_9" : "planners", "techniques_name" : "glazing (coating process)  throwing (pottery techniques)  underglazing molding (forming)  firing (technique)  stamping (marking)", "context_7" : "National Museum of Singapore"}