{
  "context_23": "1930",
  "context_24": "1939",
  "subject_terms_3": "Chinese costumes",
  "materials_name": "silk (textile)",
  "object_work_type": "robes (main garments)  silks (costume by material)",
  "object_colour": "gray (colour)",
  "physical_appearance": "This is a grey long silk robe with an underlying pinstripe weave. It buttons to the proper right of the garment.",
  "context_22": "1930s",
  "sgcool_label_text": "The long robe (known as ‘changshan’??in Southern China and Hong Kong and ‘changpao’ ?? in Northern China) was the standard informal garment worn by men during the early Republican period in China and Hong Kong. It is a one-piece long robe that can be worn alone or under a short jacket known as a ‘magua’ ??. \r\n\r\nThis robe was tailored at a certain tailor shop by the name of Lu Xin Long ???  in Hong Kong. It belonged to Mr Kaan Tat Choi, who was a successful businessman in the bullion business. Mr Kaan expanded his business from Hong Kong to Malaya in the 1920s, acquiring several rubber plantations along the east coast of Malaya. He also opened a bullion trading company called “Yee Shing” at 20 Canal Road in Singapore in the 1930s.",
  "preference": "main",
  "context_21": "20 Canal Road in Singapore",
  "title_text": "Men’s grey silk long robe (changshan) with underlying pinstripe weave",
  "creation_date": "1920s-1930s",
  "subject_terms_1": "casual wear  folk costume menswear pinstripes",
  "context_20": "Bullion Trading Company “Yee Shing”",
  "styles_periods_indexing_terms": "Chinese (culture or style)",
  "accession_no_csv": "2017-00807",
  "shape": "T-shaped?",
  "creation_place_original_location": "Hong Kong (China)  Hong Kong (China)",
  "subject_terms_2": "Robes  Ethnic costume Silk  Men's clothing  Pinstripes (Decorative arts)",
  "techniques_name": "sewing (needleworking technique)  weaving"
}