{"id":"2018-00196-060","title":"Booklet of film negatives: Negative of roads, vehicles, and people around a landform Booklet of film negatives","source":"Bumblebee","path":"./Data/json/","content":"accession_no_csv:2018-00196-060\nImage:\nobject_work_type:negatives (photographs)\ntitle_text:Booklet of film negatives: Negative of roads\n vehicles\n and people around a landform Booklet of film negatives\npreference:alternate alternate\ntitle_language:\ncreator_2:Not indicated\ncreator_1:Not indicated\ncreation_date:1950s\ncreation_place_original_location:Singapore (nation)\ninscriptions:\ninscription_language:\nshape:rectangular\nmaterials_name:paper (fiber product)\ntechniques_name:printing (process)\nobject_colour:grey monochrome\nphysical_appearance:\nsubject_terms_1:landforms (terrestrial) vehicles (transportation) people (agents)\nsubject_terms_2:Landforms Vehicles People\nsubject_terms_3:Photography\nsgcool_label_text:This booklet contains film negatives. \\r\\n","createdDate":"20201119143407","version":0,"latest":false,"roles":[],"metadata":{"accession_no_csv":"2018-00196-060","Image":"","object_work_type":"negatives (photographs)","title_text":"Booklet of film negatives: Negative of roads, vehicles, and people around a landform Booklet of film negatives","preference":"alternate alternate","title_language":"","creator_2":"Not indicated","creator_1":"Not indicated","creation_date":"1950s","creation_place_original_location":"Singapore (nation)","inscriptions":"","inscription_language":"","shape":"rectangular","materials_name":"paper (fiber product)","techniques_name":"printing (process)","object_colour":"grey monochrome","physical_appearance":"","subject_terms_1":"landforms (terrestrial) vehicles (transportation) people (agents)","subject_terms_2":"Landforms Vehicles People","subject_terms_3":"Photography","sgcool_label_text":"This booklet contains film negatives. \r\n"},"nlpDate":"20201119143407","connectorId":0,"tags":{}}