{"id":"2018-00205","title":"Board of directors of the Oversea-Chinese Banking Corporation","source":"Bumblebee","path":"./Data/json/","content":"accession_no_csv:2018-00205\nImage:\nobject_work_type:black-and-white photographs photographs\ntitle_text:Board of directors of the Oversea-Chinese Banking Corporation\npreference:main\ntitle_language:\ncreator_2:Not indicated\ncreator_1:Not indicated\ncreation_date:1936\ncreation_place_original_location:Singapore (nation)\ninscriptions:\ninscription_language:\nshape:rectangular\nmaterials_name:paper (fiber product)\ntechniques_name:printing (process) photographic processes\nobject_colour:grey monochrome\nphysical_appearance:The image shows a black-and-white photograph. It is rectangular and it features a large group of people. They make up four rows\n with the first row comprising of seated personnel. Almost everyone is in formal attire\n with a suit and a tie. The background of the photograph shows the entrances of a large building. There are inscriptions on the brown border between the photograph and the frame\n  Resolution of phootgraph is not high enough to identify more details.\nsubject_terms_1:group portraits directors (administrators) corporations\nsubject_terms_2:Portrait photography Bank directors Oversea-Chinese Banking Corporation\nsubject_terms_3:Portrait photography Corporations Oversea-Chinese Banking Corporation\nsgcool_label_text:This photograph shows the board of directors of the Oversea-Chinese Banking Corporation in 1936.","createdDate":"20201018182637","version":0,"latest":false,"roles":[],"metadata":{"accession_no_csv":"2018-00205","Image":"","object_work_type":"black-and-white photographs photographs","title_text":"Board of directors of the Oversea-Chinese Banking Corporation","preference":"main","title_language":"","creator_2":"Not indicated","creator_1":"Not indicated","creation_date":"1936","creation_place_original_location":"Singapore (nation)","inscriptions":"","inscription_language":"","shape":"rectangular","materials_name":"paper (fiber product)","techniques_name":"printing (process) photographic processes","object_colour":"grey monochrome","physical_appearance":"The image shows a black-and-white photograph. It is rectangular and it features a large group of people. They make up four rows, with the first row comprising of seated personnel. Almost everyone is in formal attire, with a suit and a tie. The background of the photograph shows the entrances of a large building. There are inscriptions on the brown border between the photograph and the frame,  Resolution of phootgraph is not high enough to identify more details.","subject_terms_1":"group portraits directors (administrators) corporations","subject_terms_2":"Portrait photography Bank directors Oversea-Chinese Banking Corporation","subject_terms_3":"Portrait photography Corporations Oversea-Chinese Banking Corporation","sgcool_label_text":"This photograph shows the board of directors of the Oversea-Chinese Banking Corporation in 1936."},"nlpDate":"20201018182637","connectorId":0,"tags":{}}