{"subject_terms_3" : "Portrait photography Lim, Herbie Eng Kwan", "materials_name" : "paper (fiber product)", "creator_2" : "Not indicated", "object_work_type" : "colour photographs photographs", "object_colour" : "multicoloured", "physical_appearance" : "The image shows a colour photograph. It consists of eight people. The front row contains three ladies and a female child. All of them are sitting down with their legs stretched, on the grass ground. Behind them are four men who are all kneeling. The man on the right hand side of the photograph is wearing a pair of sunglasses. All of them are looking towards the direction where the photograph was taken.", "sgcool_label_text" : "This photograph shows a group sitting on a lawn. It is accompanied by captions ‘Picnic at Tanah Merah’ and ‘Paul, Sam, Samuel Dec, Self, Betty Loke, May, Frances Leong, Hilary. August 1953’.   \r\n\r\nWith continuous improvement of camera technology, it became possible to take photographs outside a studio in the first decades of the 20th century. Many middle-class families collected photographs in albums as a way of documenting family life, or documentasi keluarga.", "preference" : "main", "creator_1" : "Not indicated", "title_text" : "Photograph of Herbert Lim, Mavis Chew and friends", "creation_date" : "1953", "subject_terms_1" : "studio portraits group portraits picnics", "accession_no_csv" : "2018-00183", "shape" : "rectangular", "creation_place_original_location" : "Singapore (nation)", "subject_terms_2" : "Colour photography Portrait photography Portraits, Group Picnics", "techniques_name" : "printing (process) photographic processes"}