{"subject_terms_3" : "Portrait photography Women Peranakan costumes", "materials_name" : "paper (fiber product)", "creator_2" : "Not indicated", "object_work_type" : "black-and-white photographs photographs", "object_colour" : "grey monochrome", "physical_appearance" : "The image shows a black-and-white photograph. It is rectangular and it features three ladies. All of them are dressed in their ethnic costumes. The lady on the right hand side of the photograph is looking at the two ladies, who are looking towards the direction where the photograph was captured. They are holding books and handkerchiefs in their hands.", "sgcool_label_text" : "This photograph shows three nyonyas or Eurasian women holding books and handkerchiefs in their hands. The photograph on the verso shows a group of people gathered for a festival parade. \r\n\r\nWith continuous improvement of camera technology, it became possible to take photographs outside a studio in the first decades of the 20th century. Many middle-class families collected photographs in albums as a way of documenting family life, or documentasi keluarga.", "preference" : "main alternate", "creator_1" : "Not indicated", "title_text" : "Photograph of three nyonyas Album leaf with two photographs", "creation_date" : "1910", "subject_terms_1" : "group portraits women (female humans) Peranakan folk costume", "accession_no_csv" : "2018-00160", "shape" : "rectangular", "creation_place_original_location" : "Ambon (inhabited place)", "subject_terms_2" : "Black-and-white photography Portrait photography Portraits, Group Women Peranakan (Asian people) Ethnic costume", "techniques_name" : "printing (process) photographic processes"}